{
  "prediction_tested": "Phase diagram 2D slice for open-problems/02, canonical config",
  "config": {
    "N": 48,
    "L": 20.0,
    "Lambda": -8.0,
    "T_bath": 0.001,
    "n_steps": 2000,
    "dt": 0.0025,
    "nu_fast": 10.0,
    "nu_slow": 0.5,
    "sigma_init": 0.5,
    "normalized": true
  },
  "sigma_lambda_values": [
    0.5,
    1.0,
    1.5,
    2.0,
    4.0
  ],
  "gamma_0_values": [
    0.01,
    0.05,
    0.2,
    1.0
  ],
  "grid": [
    {
      "Sigma_lambda": 0.5,
      "gamma_0": 0.01,
      "initial_peak": 1.4366912841796875,
      "max_peak": 7.482876777648926,
      "final_peak": 0.0022526588290929794,
      "final_norm": 1.6747853755950928,
      "peak_growth_ratio": 5.208409670224629,
      "final_ratio": 0.0015679491160685837,
      "regime": "released",
      "wall_time": 4.470407962799072
    },
    {
      "Sigma_lambda": 0.5,
      "gamma_0": 0.05,
      "initial_peak": 1.4366912841796875,
      "max_peak": 7.352031707763672,
      "final_peak": 0.005575879476964474,
      "final_norm": 3.757122039794922,
      "peak_growth_ratio": 5.117335776113855,
      "final_ratio": 0.0038810561032589213,
      "regime": "released",
      "wall_time": 4.514771461486816
    },
    {
      "Sigma_lambda": 0.5,
      "gamma_0": 0.2,
      "initial_peak": 1.4366912841796875,
      "max_peak": 6.732796669006348,
      "final_peak": 0.01184818521142006,
      "final_norm": 7.071330547332764,
      "peak_growth_ratio": 4.686321092878764,
      "final_ratio": 0.008246855355696723,
      "regime": "intermediate",
      "wall_time": 4.497539281845093
    },
    {
      "Sigma_lambda": 0.5,
      "gamma_0": 1.0,
      "initial_peak": 1.4366912841796875,
      "max_peak": 5.015815734863281,
      "final_peak": 0.012793898582458496,
      "final_norm": 8.058040618896484,
      "peak_growth_ratio": 3.491227231692422,
      "final_ratio": 0.00890511324411874,
      "regime": "intermediate",
      "wall_time": 4.516964673995972
    },
    {
      "Sigma_lambda": 1.0,
      "gamma_0": 0.01,
      "initial_peak": 1.4366912841796875,
      "max_peak": 7.348228454589844,
      "final_peak": 0.0023701884783804417,
      "final_norm": 1.6734694242477417,
      "peak_growth_ratio": 5.114688545483511,
      "final_ratio": 0.0016497548947919985,
      "regime": "released",
      "wall_time": 4.443343162536621
    },
    {
      "Sigma_lambda": 1.0,
      "gamma_0": 0.05,
      "initial_peak": 1.4366912841796875,
      "max_peak": 7.260396957397461,
      "final_peak": 0.005303783342242241,
      "final_norm": 3.7616093158721924,
      "peak_growth_ratio": 5.0535539801391325,
      "final_ratio": 0.003691665287209256,
      "regime": "released",
      "wall_time": 4.439341306686401
    },
    {
      "Sigma_lambda": 1.0,
      "gamma_0": 0.2,
      "initial_peak": 1.4366912841796875,
      "max_peak": 6.718781471252441,
      "final_peak": 0.010122265666723251,
      "final_norm": 7.045736789703369,
      "peak_growth_ratio": 4.6765659019701555,
      "final_ratio": 0.007045539830432532,
      "regime": "intermediate",
      "wall_time": 4.444175481796265
    },
    {
      "Sigma_lambda": 1.0,
      "gamma_0": 1.0,
      "initial_peak": 1.4366912841796875,
      "max_peak": 4.944893836975098,
      "final_peak": 0.012528952211141586,
      "final_norm": 8.012286186218262,
      "peak_growth_ratio": 3.441862487387818,
      "final_ratio": 0.008720698976255908,
      "regime": "intermediate",
      "wall_time": 4.505079746246338
    },
    {
      "Sigma_lambda": 1.5,
      "gamma_0": 0.01,
      "initial_peak": 1.4366912841796875,
      "max_peak": 7.221630096435547,
      "final_peak": 0.002033267403021455,
      "final_norm": 1.6582618951797485,
      "peak_growth_ratio": 5.026570548563539,
      "final_ratio": 0.001415243083473146,
      "regime": "released",
      "wall_time": 4.5374157428741455
    },
    {
      "Sigma_lambda": 1.5,
      "gamma_0": 0.05,
      "initial_peak": 1.4366912841796875,
      "max_peak": 7.074965953826904,
      "final_peak": 0.005163446068763733,
      "final_norm": 3.7351303100585938,
      "peak_growth_ratio": 4.924485887632096,
      "final_ratio": 0.0035939844040412086,
      "regime": "intermediate",
      "wall_time": 4.453143358230591
    },
    {
      "Sigma_lambda": 1.5,
      "gamma_0": 0.2,
      "initial_peak": 1.4366912841796875,
      "max_peak": 7.025285720825195,
      "final_peak": 0.014081479050219059,
      "final_norm": 7.059539318084717,
      "peak_growth_ratio": 4.889906271573469,
      "final_ratio": 0.009801325591154545,
      "regime": "intermediate",
      "wall_time": 4.483850955963135
    },
    {
      "Sigma_lambda": 1.5,
      "gamma_0": 1.0,
      "initial_peak": 1.4366912841796875,
      "max_peak": 4.888552188873291,
      "final_peak": 0.013746993616223335,
      "final_norm": 8.032918930053711,
      "peak_growth_ratio": 3.4026462349317614,
      "final_ratio": 0.009568509092802427,
      "regime": "intermediate",
      "wall_time": 4.405129432678223
    },
    {
      "Sigma_lambda": 2.0,
      "gamma_0": 0.01,
      "initial_peak": 1.4366912841796875,
      "max_peak": 7.228955268859863,
      "final_peak": 0.002616139594465494,
      "final_norm": 1.6675835847854614,
      "peak_growth_ratio": 5.0316691891030745,
      "final_ratio": 0.0018209476338260382,
      "regime": "released",
      "wall_time": 4.534740447998047
    },
    {
      "Sigma_lambda": 2.0,
      "gamma_0": 0.05,
      "initial_peak": 1.4366912841796875,
      "max_peak": 7.271942615509033,
      "final_peak": 0.006052782759070396,
      "final_norm": 3.770803928375244,
      "peak_growth_ratio": 5.061590263395465,
      "final_ratio": 0.004213001655763767,
      "regime": "released",
      "wall_time": 4.510456800460815
    },
    {
      "Sigma_lambda": 2.0,
      "gamma_0": 0.2,
      "initial_peak": 1.4366912841796875,
      "max_peak": 7.293066024780273,
      "final_peak": 0.010638721287250519,
      "final_norm": 7.05677604675293,
      "peak_growth_ratio": 5.076293080558654,
      "final_ratio": 0.007405015541195369,
      "regime": "released",
      "wall_time": 4.397568464279175
    },
    {
      "Sigma_lambda": 2.0,
      "gamma_0": 1.0,
      "initial_peak": 1.4366912841796875,
      "max_peak": 4.564556121826172,
      "final_peak": 0.012957668863236904,
      "final_norm": 8.030912399291992,
      "peak_growth_ratio": 3.177130794965748,
      "final_ratio": 0.009019104525740469,
      "regime": "intermediate",
      "wall_time": 4.5594563484191895
    },
    {
      "Sigma_lambda": 4.0,
      "gamma_0": 0.01,
      "initial_peak": 1.4366912841796875,
      "max_peak": 8.361943244934082,
      "final_peak": 0.0034281613770872355,
      "final_norm": 1.6666172742843628,
      "peak_growth_ratio": 5.820278397323563,
      "final_ratio": 0.0023861503266824815,
      "regime": "released",
      "wall_time": 4.4310455322265625
    },
    {
      "Sigma_lambda": 4.0,
      "gamma_0": 0.05,
      "initial_peak": 1.4366912841796875,
      "max_peak": 8.25186538696289,
      "final_peak": 0.005535459145903587,
      "final_norm": 3.754133939743042,
      "peak_growth_ratio": 5.743659391429027,
      "final_ratio": 0.0038529217841425044,
      "regime": "released",
      "wall_time": 4.511791467666626
    },
    {
      "Sigma_lambda": 4.0,
      "gamma_0": 0.2,
      "initial_peak": 1.4366912841796875,
      "max_peak": 7.630105972290039,
      "final_peak": 0.00991160236299038,
      "final_norm": 7.051545143127441,
      "peak_growth_ratio": 5.310887632096012,
      "final_ratio": 0.006898908952906776,
      "regime": "released",
      "wall_time": 4.511076927185059
    },
    {
      "Sigma_lambda": 4.0,
      "gamma_0": 1.0,
      "initial_peak": 1.4366912841796875,
      "max_peak": 2.7047863006591797,
      "final_peak": 0.011112814769148827,
      "final_norm": 8.04171371459961,
      "peak_growth_ratio": 1.8826496203069407,
      "final_ratio": 0.007735005349805507,
      "regime": "dispersive",
      "wall_time": 4.5572593212127686
    }
  ],
  "regime_counts": {
    "released": 11,
    "intermediate": 8,
    "dispersive": 1
  },
  "wall_time_total_s": 90.0635347366333,
  "backend": "cupy"
}